SAPLaMa/__init__.py
SAPLaMa/activity.py
SAPLaMa/connection.py
SAPLaMa/lama.py
SAPLaMa-0.0.6.dist-info/LICENSE
SAPLaMa-0.0.6.dist-info/METADATA
SAPLaMa-0.0.6.dist-info/WHEEL
SAPLaMa-0.0.6.dist-info/top_level.txt
SAPLaMa-0.0.6.dist-info/RECORD
