Metadata-Version: 2.1
Name: SAPLaMa
Version: 0.0.6
Summary: SAP LAMA API made easy
Home-page: https://git.tech.rz.db.de/sapzs/python_sap_lama_api
Author: Maximilian Wiederer
Author-email: maximilian.wiederer@deutschebahn.com
Maintainer: Maximilian Wiederer
Maintainer-email: maximilian.wiederer@deutschebahn.com
License: Apache License 2.0
Platform: UNKNOWN
Classifier: Development Status :: 2 - Pre-Alpha
Classifier: Intended Audience :: Developers
Classifier: License :: OSI Approved :: Apache Software License
Classifier: Topic :: Software Development :: Libraries
Classifier: Programming Language :: Python
Classifier: Programming Language :: Python :: 3 :: Only
Classifier: Programming Language :: Python :: 3.8
Classifier: Programming Language :: Python :: 3.7
Classifier: Operating System :: OS Independent
Requires-Python: >=3.7
License-File: LICENSE
Requires-Dist: requests
